arpespythontools/__init__.py
arpespythontools/crop_2d.py
arpespythontools/custom_loader_one.py
arpespythontools/cv2d.py
arpespythontools/export_itx.py
arpespythontools/import_itx.py
arpespythontools/k_conv.py
arpespythontools/k_conv3d.py
arpespythontools/k_conv3d_mp.py
arpespythontools/k_conv3d_mp_alt.py
arpespythontools/laplacian.py
arpespythontools/line_profile.py
arpespythontools/load_ses_map.py
arpespythontools/load_ses_spectra.py
arpespythontools/plane_slice.py
arpespythontools/rotate_2d.py
arpespythontools/rotate_3d.py
arpespythontools/save_xps.py
arpespythontools-1.2.2.dist-info/LICENSE
arpespythontools-1.2.2.dist-info/METADATA
arpespythontools-1.2.2.dist-info/WHEEL
arpespythontools-1.2.2.dist-info/RECORD
