Metadata-Version: 2.3
Name: arpespythontools
Version: 1.2.2
Summary: Explore, analyze, visualize Angle Resolved Photoemission Spectroscopy (ARPES) data.
Home-page: https://pranabdas.github.io/arpespythontools/
License: MIT
Keywords: arpes,condensed-matter-physics,data-analysis,materials-science,matplotlib,photoelectron-spectroscopy,python,surface-science
Author: Pranab Das
Requires-Python: >=3.10,<4.0
Classifier: License :: OSI Approved :: MIT License
Classifier: Programming Language :: Python :: 3
Classifier: Programming Language :: Python :: 3.10
Classifier: Programming Language :: Python :: 3.11
Classifier: Programming Language :: Python :: 3.12
Classifier: Programming Language :: Python :: 3.13
Provides-Extra: lint
Provides-Extra: notebook
Requires-Dist: astropy (>=6.1.7)
Requires-Dist: autopep8 (>=2.3.1) ; extra == "lint"
Requires-Dist: jupyterlab (>=4.3.4) ; extra == "notebook"
Requires-Dist: matplotlib (>=3.10.0)
Requires-Dist: numpy (>=2.2.1)
Requires-Dist: psutil (>=6.1.1)
Requires-Dist: scipy (>=1.15.0)
Project-URL: Documentation, https://pranabdas.github.io/arpespythontools/docs/
Project-URL: Repository, https://github.com/pranabdas/arpespythontools
